QuoteBook/QuoteBook.py
QuoteBook/QuoteBook_pl.qm
QuoteBook/__init__.py
QuoteBook/editordialog.py
QuoteBook/icon.ico
QuoteBook/quotelistdesign.py
QuoteBook/resources.py
QuoteBook/settings.py
QuoteBook/settingsdialog.py
QuoteBook/sqv.py
QuoteBook/sqw.py
QuoteBook-1.0.12.dist-info/DESCRIPTION.rst
QuoteBook-1.0.12.dist-info/METADATA
QuoteBook-1.0.12.dist-info/RECORD
QuoteBook-1.0.12.dist-info/WHEEL
QuoteBook-1.0.12.dist-info/entry_points.txt
QuoteBook-1.0.12.dist-info/metadata.json
QuoteBook-1.0.12.dist-info/top_level.txt
